autowatch/__init__.py
autowatch/app.py
autowatch/config.py
autowatch/data.py
auto_timewatch-2.0.dist-info/LICENSE
auto_timewatch-2.0.dist-info/METADATA
auto_timewatch-2.0.dist-info/WHEEL
auto_timewatch-2.0.dist-info/top_level.txt
auto_timewatch-2.0.dist-info/RECORD
