Metadata-Version: 2.1
Name: auto-timewatch
Version: 2.0
Summary: Automatic hour fill for TimeWatch
Home-page: https://github.com/danielattiach/autowatch
Author: Daniel Attiach
License: MIT
Platform: UNKNOWN
Requires-Dist: beautifulsoup4 (==4.11.1)
Requires-Dist: python-dotenv (==0.10.5)
Requires-Dist: requests (==2.27.1)
